MANIFEST.in
setup.py
flask_views/__init__.py
flask_views/modelview.py
flask_views/utils.py
flask_views/view.py
flask_views/tests/__init__.py
paqmind.flask_views.egg-info/PKG-INFO
paqmind.flask_views.egg-info/SOURCES.txt
paqmind.flask_views.egg-info/dependency_links.txt
paqmind.flask_views.egg-info/requires.txt
paqmind.flask_views.egg-info/top_level.txt