Metadata-Version: 1.0
Name: paqmind.flask-views
Version: 0.4.5
Summary: Class-based views for Flask
Home-page: UNKNOWN
Author: UNKNOWN
Author-email: UNKNOWN
License: MIT
Platform: UNKNOWN
